sample_data/__init__.py
sample_data/dataset.py
sample_data/data/airbnb.csv
sample_data/data/corona.csv
sample_data/data/countries.csv
sample_data/data/drinks.csv
sample_data/data/iris.csv
sample_data/data/titanic.csv
sample_data-0.1.0.dist-info/METADATA
sample_data-0.1.0.dist-info/WHEEL
sample_data-0.1.0.dist-info/top_level.txt
sample_data-0.1.0.dist-info/RECORD
