Metadata-Version: 2.1
Name: sample-data
Version: 0.1.0
Summary: A few sample datasets
Home-page: https://github.com/joelhoro/sample_data
Author: Joel Horowitz
Author-email: joelhoro@gmail.com
License: UNKNOWN
Platform: UNKNOWN
Classifier: Programming Language :: Python :: 3
Classifier: License :: OSI Approved :: MIT License
Classifier: Operating System :: OS Independent
Requires-Python: >=3.6
Requires-Dist: pandas
